peewee_validates.py
peewee_validates-1.0.7.dist-info/DESCRIPTION.rst
peewee_validates-1.0.7.dist-info/METADATA
peewee_validates-1.0.7.dist-info/RECORD
peewee_validates-1.0.7.dist-info/WHEEL
peewee_validates-1.0.7.dist-info/metadata.json
peewee_validates-1.0.7.dist-info/top_level.txt
